beauris/__init__.py
beauris/annotation.py
beauris/assembly.py
beauris/beauris.py
beauris/blastbank.py
beauris/config.py
beauris/data_locker.py
beauris/expression_data.py
beauris/extra_file.py
beauris/job_runner.py
beauris/managed_entity.py
beauris/managed_file.py
beauris/mr_bot.py
beauris/organism.py
beauris/proteome.py
beauris/raw_data_greeters.py
beauris/task.py
beauris/track.py
beauris/transcriptome.py
beauris/util.py
beauris/deployers/__init__.py
beauris/deployers/authelia.py
beauris/deployers/basedeployer.py
beauris/deployers/blast.py
beauris/deployers/deployers.py
beauris/deployers/dockercompose.py
beauris/deployers/download.py
beauris/deployers/elasticsearch.py
beauris/deployers/genoboo.py
beauris/deployers/genomehomepage.py
beauris/deployers/jbrowse.py
beauris/es_parsers/__init__.py
beauris/es_parsers/diamond_parser.py
beauris/es_parsers/eggnog_parser.py
beauris/es_parsers/gff_parser.py
beauris/es_parsers/interpro_parser.py
beauris/tasks/__init__.py
beauris/tasks/annotation.py
beauris/tasks/assembly.py
beauris/tasks/organism.py
beauris/tasks/proteome.py
beauris/tasks/tasks.py
beauris/tasks/track.py
beauris/tasks/transcriptome.py
beauris/validation/__init__.py
beauris/validation/ogs/__init__.py
beauris/validation/ogs/fasta_check.py
beauris/validation/ogs/ogs_check.py
beauris/validation/template/__init__.py
beauris/validation/template/ext.py
beauris/validation/template/schema.yaml
beauris/workflows/__init__.py
beauris/workflows/minimal.bam
beauris/workflows/minimal.wg
beauris/workflows/ansible/ansible_data/project/playbook_deploy.yml
beauris/workflows/ansible/ansible_data/project/playbook_shutdown.yml
beauris/workflows/ansible/ansible_data/project/playbook_update.yml
beauris/workflows/ansible/docker_files/postgres-blast-entrypoint.sh
beauris/workflows/ansible/templates/default.conf.j2
beauris/workflows/ansible/templates/docker-compose.yml.j2
beauris/workflows/ansible/templates/genoboo.json.j2
beauris/workflows/ansible/templates/web/index.html.j2
beauris-0.4.dist-info/LICENSE
beauris-0.4.dist-info/METADATA
beauris-0.4.dist-info/WHEEL
beauris-0.4.dist-info/top_level.txt
beauris-0.4.dist-info/RECORD
