Metadata-Version: 2.1
Name: beauris
Version: 0.4
Summary: BEAURIS: an automated system for the creation of genome portals
Home-page: https://gitlab.com/beaur1s/beauris
Author: BEAURIS team
Author-email: gogepp@inrae.fr
License: MIT
Platform: Posix
Classifier: Development Status :: 4 - Beta
Classifier: Intended Audience :: Developers
Classifier: License :: OSI Approved :: MIT License
Classifier: Operating System :: OS Independent
Classifier: Topic :: Scientific/Engineering
Classifier: Programming Language :: Python :: 3.9
License-File: LICENSE
Requires-Dist: pyyaml
Requires-Dist: bioblend
Requires-Dist: drmaa
Requires-Dist: gopublic
Requires-Dist: envsubst
Requires-Dist: python-gitlab
Requires-Dist: Jinja2
Requires-Dist: ansible
Requires-Dist: ansible-runner
Requires-Dist: pykwalify
Requires-Dist: requests
